indusmes/__init__.py
indusmes/icons_rc.py
indusmes/main.py
indusmes/__pycache__/icons_rc.cpython-310.pyc
indusmes/assets/__init__.py
indusmes/backend/__init__.py
indusmes/backend/config.json
indusmes/backend/downtime_reasons.json
indusmes/backend/sensor.py
indusmes/backend/__pycache__/__init__.cpython-310.pyc
indusmes/backend/__pycache__/sensor.cpython-310.pyc
indusmes/complete/__init__.py
indusmes/complete/complete_dialog.py
indusmes/complete/ui_complete_dialog.py
indusmes/complete/__pycache__/__init__.cpython-310.pyc
indusmes/complete/__pycache__/complete_dialog.cpython-310.pyc
indusmes/complete/__pycache__/ui_complete_dialog.cpython-310.pyc
indusmes/downtime_dialog/__init__.py
indusmes/downtime_dialog/dowmtime_dialog.py
indusmes/downtime_dialog/ui_downtime_dialog.py
indusmes/downtime_dialog/__pycache__/__init__.cpython-310.pyc
indusmes/downtime_dialog/__pycache__/dowmtime_dialog.cpython-310.pyc
indusmes/downtime_dialog/__pycache__/ui_downtime_dialog.cpython-310.pyc
indusmes/home/__init__.py
indusmes/home/home.py
indusmes/home/ui_home.py
indusmes/home/__pycache__/__init__.cpython-310.pyc
indusmes/home/__pycache__/home.cpython-310.pyc
indusmes/home/__pycache__/ui_home.cpython-310.pyc
indusmes/job_card/__init__.py
indusmes/job_card/job_card.py
indusmes/job_card/ui_job_card.py
indusmes/job_card/__pycache__/__init__.cpython-310.pyc
indusmes/job_card/__pycache__/job_card.cpython-310.pyc
indusmes/job_card/__pycache__/ui_job_card.cpython-310.pyc
indusmes/ongoing_job_alert/__init__.py
indusmes/ongoing_job_alert/ongoing_job_alert_dialog.py
indusmes/ongoing_job_alert/ui_ongoing_job_alert_dialog.py
indusmes/ongoing_job_alert/__pycache__/__init__.cpython-310.pyc
indusmes/ongoing_job_alert/__pycache__/ongoing_job_alert_dialog.cpython-310.pyc
indusmes/ongoing_job_alert/__pycache__/ui_ongoing_job_alert_dialog.cpython-310.pyc
indusmes/progress/__init__.py
indusmes/progress/progress_dialog.py
indusmes/progress/ui_progress_dialog.py
indusmes-1.0.1.dist-info/METADATA
indusmes-1.0.1.dist-info/WHEEL
indusmes-1.0.1.dist-info/entry_points.txt
indusmes-1.0.1.dist-info/top_level.txt
indusmes-1.0.1.dist-info/RECORD
